LICENSE
MANIFEST.in
README.rst
setup.cfg
setup.py
src/testing/__init__.py
src/testing/elasticsearch.py
src/testing.elasticsearch6.egg-info/PKG-INFO
src/testing.elasticsearch6.egg-info/SOURCES.txt
src/testing.elasticsearch6.egg-info/dependency_links.txt
src/testing.elasticsearch6.egg-info/namespace_packages.txt
src/testing.elasticsearch6.egg-info/requires.txt
src/testing.elasticsearch6.egg-info/top_level.txt
tests/test_elasticsearch.py