Metadata-Version: 2.1
Name: testing.elasticsearch6
Version: 1.1.0
Summary: automatically setups a elasticsearch instance in a temporary directory, and destroys it after testing
Home-page: https://github.com/criteo-forks/testing.elasticsearch
Maintainer: Criteo Observability Team
Maintainer-email: sre-observability@criteo.com
License: Apache License 2.0
Platform: UNKNOWN
Classifier: Development Status :: 4 - Beta
Classifier: Intended Audience :: Developers
Classifier: License :: OSI Approved :: Apache Software License
Classifier: Programming Language :: Python
Classifier: Programming Language :: Python :: 2.7
Classifier: Programming Language :: Python :: 3.6
Classifier: Topic :: Database
Classifier: Topic :: Software Development
Classifier: Topic :: Software Development :: Testing
Provides-Extra: testing
